mangadm/__init__.py
mangadm/assets/__init__.py
mangadm/components/__init__.py
mangadm/components/logger.py
mangadm/components/progress_bar.py
mangadm/components/signal_handler.py
mangadm/components/stats_manager.py
mangadm/core/__init__.py
mangadm/core/cli.py
mangadm/core/downloader.py
mangadm/core/mangadm.py
mangadm/utils/__init__.py
mangadm/utils/utility.py
MangaDM-0.6.0.dist-info/METADATA
MangaDM-0.6.0.dist-info/WHEEL
MangaDM-0.6.0.dist-info/entry_points.txt
MangaDM-0.6.0.dist-info/top_level.txt
MangaDM-0.6.0.dist-info/RECORD
