Metadata-Version: 2.1
Name: MangaDM
Version: 0.6.0
Home-page: https://github.com/xMohnad/MangaDM
Classifier: Programming Language :: Python :: 3
Classifier: License :: OSI Approved :: MIT License
Classifier: Operating System :: OS Independent
Requires-Dist: requests
Requires-Dist: click
Requires-Dist: rich
Requires-Dist: InquirerPy
Requires-Dist: ebooklib
Requires-Dist: auto_click_auto
